mappyng/__init__.py
mappyng/arithmedict.py
mappyng/diagnosis.py
mappyng/get.py
mappyng/manip.py
mappyng/my_partial_mongoquery.py
mappyng/ot.py
mappyng/special.py
mappyng/to.py
mappyng-0.0.3.dist-info/LICENSE
mappyng-0.0.3.dist-info/METADATA
mappyng-0.0.3.dist-info/WHEEL
mappyng-0.0.3.dist-info/top_level.txt
mappyng-0.0.3.dist-info/RECORD
