Metadata-Version: 2.1
Name: mappyng
Version: 0.0.3
Summary: Utils to work with python dictionaries.
Home-page: https://github.com/thorwhalen/newut/tree/master/mappyng
Author: Thor Whalen
License: mit
Platform: any
License-File: LICENSE
